{
  "name": "${name}",
  "version": "0.1.0",
  "description": "",
  "main": "index.js",
  "scripts": {
  },
  "author": "",
  "license": "MIT",
  "dependencies": {
  },
  "devDependencies": {
    "css-loader": "^0.28.11",
    "file-loader": "^1.1.11",
    "html-loader": "^0.5.5",
    "node-sass": "^4.9.0",
    "postcss-loader": "^2.1.5",
    "pug": "^2.0.3",
    "pug-loader": "^2.4.0",
    "sass-loader": "^7.0.1",
    "style-loader": "^0.21.0",
    "ts-loader": "^3.5.0",
    "typescript": "^2.7.1",
    "url-loader": "^0.6.2",
    "webpack": "^3.11.0",
    "webpack-dev-server": "^2.11.2"
  }
}